{
  "localized title": "A Nightmare on Elm Street 3: Dream Warriors",
  "cast": [
    {
      "personID": "0000486",
      "name": "Heather Langenkamp",
      "character": "Nancy Thompson"
    },
    {
      "personID": "0913738",
      "name": "Craig Wasson",
      "character": "Neil Gordon"
    },
    {
      "personID": "0000099",
      "name": "Patricia Arquette",
      "character": "Kristen Parker"
    },
    {
      "personID": "0000387",
      "name": "Robert Englund",
      "character": "Freddy Krueger"
    },
    {
      "personID": "0756209",
      "name": "Ken Sagoes",
      "character": "Kincaid"
    },
    {
      "personID": "0247672",
      "name": "Rodney Eastman",
      "character": "Joey"
    },
    {
      "personID": "0748075",
      "name": "Jennifer Rubin",
      "character": "Taryn"
    },
    {
      "personID": "0339562",
      "name": "Bradley Gregg",
      "character": "Phillip"
    },
    {
      "personID": "0373934",
      "name": "Ira Heiden",
      "character": "Will"
    },
    {
      "personID": "0000401",
      "name": "Laurence Fishburne",
      "character": "Max"
    },
    {
      "personID": "0837238",
      "name": "Penelope Sudrow",
      "character": "Jennifer"
    },
    {
      "personID": "0768334",
      "name": "John Saxon",
      "character": "Lt. Thompson"
    },
    {
      "personID": "0688467",
      "name": "Priscilla Pointer",
      "character": "Dr. Elizabeth Simms"
    },
    {
      "personID": "0484707",
      "name": "Clayton Landey",
      "character": "Lorenzo"
    },
    {
      "personID": "0120401",
      "name": "Brooke Bundy",
      "character": "Elaine Parker"
    },
    {
      "personID": "0165731",
      "name": "Kristen Clayton",
      "character": "Little Girl"
    },
    {
      "personID": "0684932",
      "name": "Sally Piper",
      "character": "Nurse #1"
    },
    {
      "personID": "0815164",
      "name": "Rozlyn Sorrell",
      "character": "Nurse #2"
    },
    {
      "personID": "0552832",
      "name": "Nan Martin",
      "character": "Nun"
    },
    {
      "personID": "0017499",
      "name": "Stacey Alden",
      "character": "Marcie"
    },
    {
      "personID": "0147118",
      "name": "Dick Cavett",
      "character": "Dick Cavett"
    },
    {
      "personID": "0001248",
      "name": "Zsa Zsa Gabor",
      "character": "Zsa Zsa Gabor"
    },
    {
      "personID": "0745606",
      "name": "Michael Rougas",
      "character": "Priest in Church"
    },
    {
      "personID": "0790280",
      "name": "Jack Shea",
      "character": "Priest in Cemetery"
    },
    {
      "personID": "0448824",
      "name": "Paul Kent",
      "character": "Dr. Carver"
    },
    {
      "personID": "0114219",
      "name": "Mary Brown",
      "character": "Neurosurgeon"
    },
    {
      "personID": "0230041",
      "name": "Melanie Doctors",
      "character": "Girl in Cemetery"
    },
    {
      "personID": "0244069",
      "name": "Donna Durham",
      "character": "Girl in Crowd"
    },
    {
      "personID": "7907141",
      "name": "Crystal Echeverria Adams",
      "character": "Freddy song singer"
    },
    {
      "personID": "7907142",
      "name": "Trisha Lawson Adams",
      "character": "Freddy song singer"
    },
    {
      "personID": "2384703",
      "name": "John Besmehn",
      "character": "Templeton Smithee"
    }
  ],
  "genres": [
    "Fantasy",
    "Horror"
  ],
  "runtimes": [
    "96"
  ],
  "countries": [
    "United States"
  ],
  "country codes": [
    "us"
  ],
  "language codes": [
    "en"
  ],
  "color info": [
    "Color"
  ],
  "aspect ratio": "1.85 : 1",
  "sound mix": [
    "Mono",
    "Dolby::(DVD re-release)"
  ],
  "box office": {
    "Budget": "$4,500,000 (estimated)",
    "Opening Weekend United States": "$8,880,555, 01 Mar 1987"
  },
  "certificates": [
    "Argentina:16",
    "Australia:M",
    "Brazil:18",
    "Canada:14A::(Alberta)",
    "Canada:R::(Canadian Home Video rating)",
    "Canada:R::(Manitoba/Nova Scotia/Ontario)",
    "Canada:18+::(Quebec)",
    "Canada:13+::(Quebec)",
    "Chile:16+::(Netflix self-rating)",
    "Denmark:15",
    "Finland:K-16",
    "Finland:K-18",
    "France:12 avec avertissement::(new rating)",
    "France:13",
    "Germany:BPjM Restricted",
    "Germany:16",
    "Germany:18::(BPjM restricted)",
    "Hungary:18",
    "Iceland:16",
    "India:UA::(TV)",
    "Ireland:18",
    "Italy:VM14",
    "Mexico:C",
    "Mexico:B",
    "Netherlands:16",
    "New Zealand:M",
    "Norway:15::(recommended rating)",
    "Norway:18::(video premiere)",
    "Norway:(Banned)::(1988-2003)",
    "Poland:16",
    "Portugal:M/18",
    "Russia:18+",
    "Singapore:M18",
    "South Africa:16",
    "South Korea:18::(VHS/DVD rating)",
    "South Korea:19::(tv rating)",
    "South Korea:12::(theatrical rating)",
    "Spain:13",
    "Spain:12",
    "Sweden:15",
    "United Kingdom:18",
    "United States:R",
    "West Germany:18"
  ],
  "original air date": "27 Feb 1987 (USA)",
  "rating": 6.6,
  "votes": 85094,
  "cover url": "https://m.media-amazon.com/images/M/MV5BMjFkYTEwNjAtYWU1YS00NTMyLTkwYmUtZjEyMjZjMDg5Njc5XkEyXkFqcGdeQXVyMTQxNzMzNDI@._V1_SX101_CR0,0,101,150_.jpg",
  "imdbID": "0093629",
  "videos": [
    "http://www.imdb.com/title/tt0093629/videoplayer/vi2696151321",
    "http://www.imdb.com/title/tt0093629/videoplayer/vi2135342617"
  ],
  "plot outline": "Picking up where the original Nightmare left off, Nancy has grown up and become a psychiatrist specializing in dream therapy. She meets a group of children at a local hospital facing Freddy Krueger, the same demon she once encountered in her sleep. One of them is Kristen, who has the power to draw other people into her dreams. Working with a male doctor assigned to the case, Nancy helps the kids realize their special abilities within the nightmare world. When Freddy captures one of her charges, she leads a rescue attempt into Krueger's domain, in hopes of putting his spirit to rest once and for all.",
  "languages": [
    "English"
  ],
  "title": "A Nightmare on Elm Street 3: Dream Warriors",
  "year": 1987,
  "kind": "movie",
  "original title": "A Nightmare on Elm Street 3: Dream Warriors",
  "director": [
    {
      "personID": "0751080",
      "name": "Chuck Russell",
      "character": null
    }
  ],
  "writer": [
    {
      "personID": "0000127",
      "name": "Wes Craven",
      "character": null
    },
    {
      "personID": "0905818",
      "name": "Bruce Wagner",
      "character": null
    },
    {
      "personID": null,
      "name": null,
      "character": null
    },
    {
      "personID": "0000127",
      "name": "Wes Craven",
      "character": null
    },
    {
      "personID": "0905818",
      "name": "Bruce Wagner",
      "character": null
    },
    {
      "personID": "0001104",
      "name": "Frank Darabont",
      "character": null
    },
    {
      "personID": "0751080",
      "name": "Chuck Russell",
      "character": null
    },
    {
      "personID": null,
      "name": null,
      "character": null
    },
    {
      "personID": "0000127",
      "name": "Wes Craven",
      "character": null
    }
  ],
  "producer": [
    {
      "personID": "0000127",
      "name": "Wes Craven",
      "character": null
    },
    {
      "personID": "0226044",
      "name": "Stephen Diener",
      "character": null
    },
    {
      "personID": "0555550",
      "name": "Niki Marvin",
      "character": null
    },
    {
      "personID": "0728260",
      "name": "Sara Risher",
      "character": null
    },
    {
      "personID": "0790144",
      "name": "Robert Shaye",
      "character": null
    },
    {
      "personID": "0003080",
      "name": "Rachel Talalay",
      "character": null
    },
    {
      "personID": "0860737",
      "name": "Steve Thompson",
      "character": null
    }
  ],
  "composer": [
    {
      "personID": "0000823",
      "name": "Angelo Badalamenti",
      "character": null
    }
  ],
  "cinematographer": [
    {
      "personID": "0906096",
      "name": "Roy H. Wagner",
      "character": null
    }
  ],
  "editor": [
    {
      "personID": "0831395",
      "name": "Terry Stokes",
      "character": null
    },
    {
      "personID": "0918944",
      "name": "Chuck Weiss",
      "character": null
    }
  ],
  "editorial department": [
    {
      "personID": "0426129",
      "name": "Rolf Johnson",
      "character": null
    }
  ],
  "casting director": [
    {
      "personID": "0072438",
      "name": "Annette Benson",
      "character": null
    }
  ],
  "art direction": [
    {
      "personID": "0833950",
      "name": "C.J. Strawn",
      "character": null
    },
    {
      "personID": "0833954",
      "name": "Mick Strawn",
      "character": null
    }
  ],
  "set decoration": [
    {
      "personID": "0057891",
      "name": "James R. Barrows",
      "character": null
    }
  ],
  "costume designer": [
    {
      "personID": "0775453",
      "name": "Camile Morris",
      "character": null
    }
  ],
  "make up": [
    {
      "personID": "0134148",
      "name": "Greg Cannom",
      "character": null
    },
    {
      "personID": "0170091",
      "name": "H. Wayne Coker",
      "character": null
    },
    {
      "personID": "0253761",
      "name": "Mike Elizalde",
      "character": null
    },
    {
      "personID": "0313608",
      "name": "Screaming Mad George",
      "character": null
    },
    {
      "personID": "0542398",
      "name": "Lou Manigan",
      "character": null
    },
    {
      "personID": "0542838",
      "name": "Kelly Mann",
      "character": null
    },
    {
      "personID": "0612817",
      "name": "Matthew W. Mungle",
      "character": null
    },
    {
      "personID": "0671883",
      "name": "Brian Penikas",
      "character": null
    },
    {
      "personID": "0720646",
      "name": "Christa Reusch",
      "character": null
    },
    {
      "personID": "0795197",
      "name": "Mark Shostrom",
      "character": null
    },
    {
      "personID": "0944892",
      "name": "Kevin Yagher",
      "character": null
    }
  ],
  "production manager": [
    {
      "personID": "0277688",
      "name": "Joe Fineman",
      "character": null
    },
    {
      "personID": "0647910",
      "name": "Gerald T. Olson",
      "character": null
    }
  ],
  "assistant director": [
    {
      "personID": "0257258",
      "name": "Robert Engelman",
      "character": null
    },
    {
      "personID": "0536564",
      "name": "Dennis Maguire",
      "character": null
    },
    {
      "personID": "0646981",
      "name": "Robin R. Oliver",
      "character": null
    },
    {
      "personID": "0674635",
      "name": "Dan Perri",
      "character": null
    }
  ],
  "art department": [
    {
      "personID": "0134177",
      "name": "David T. Cannon",
      "character": null
    },
    {
      "personID": "0192285",
      "name": "David Cunningham",
      "character": null
    },
    {
      "personID": "0246778",
      "name": "C\u00e9sar D\u00edez \u00c1lava",
      "character": null
    },
    {
      "personID": "0333833",
      "name": "Batia Grafka",
      "character": null
    },
    {
      "personID": "0640535",
      "name": "Thomas A. O'Conor",
      "character": null
    },
    {
      "personID": "0794782",
      "name": "Babak Shokrian",
      "character": null
    },
    {
      "personID": "0903001",
      "name": "Pete von Sholly",
      "character": null
    },
    {
      "personID": "0651574",
      "name": "Kelly Osborn",
      "character": null
    },
    {
      "personID": "3749511",
      "name": "Matthew Joseph Peak",
      "character": null
    }
  ],
  "sound crew": [
    {
      "personID": "0275864",
      "name": "William Fiege",
      "character": null
    },
    {
      "personID": "0001892",
      "name": "Steve Rice",
      "character": null
    },
    {
      "personID": "0769957",
      "name": "William Shaffer",
      "character": null
    },
    {
      "personID": "0947884",
      "name": "David Lewis Yewdall",
      "character": null
    }
  ],
  "special effects": [
    {
      "personID": "0042138",
      "name": "Jim Aupperle",
      "character": null
    },
    {
      "personID": "0069406",
      "name": "James Belohovek",
      "character": null
    },
    {
      "personID": "0079068",
      "name": "Doug Beswick",
      "character": null
    },
    {
      "personID": "0081861",
      "name": "R. Christopher Biggs",
      "character": null
    },
    {
      "personID": "0131011",
      "name": "Yancy Calzada",
      "character": null
    },
    {
      "personID": "0156251",
      "name": "Peter Chesney",
      "character": null
    },
    {
      "personID": "0156256",
      "name": "Tom Chesney",
      "character": null
    },
    {
      "personID": "0006866",
      "name": "Robin L. D'Arcy",
      "character": null
    },
    {
      "personID": "0282037",
      "name": "Joel Fletcher",
      "character": null
    },
    {
      "personID": "1062266",
      "name": "Edward J. Franklin",
      "character": null
    },
    {
      "personID": "0319426",
      "name": "Christopher Gilman",
      "character": null
    },
    {
      "personID": "0370924",
      "name": "Bruce D. Hayes",
      "character": null
    },
    {
      "personID": "1654197",
      "name": "David Hill",
      "character": null
    },
    {
      "personID": "0453139",
      "name": "Crit Killen",
      "character": null
    },
    {
      "personID": "0533086",
      "name": "Terry Mack",
      "character": null
    },
    {
      "personID": "0568660",
      "name": "Brian McFadden",
      "character": null
    },
    {
      "personID": "0613017",
      "name": "Bernardo F. Munoz",
      "character": null
    },
    {
      "personID": "1611150",
      "name": "Larry Nikolai",
      "character": null
    },
    {
      "personID": "0644072",
      "name": "Larry Odien",
      "character": null
    },
    {
      "personID": "0697934",
      "name": "D. Kerry Prior",
      "character": null
    },
    {
      "personID": "0829812",
      "name": "Sandra Stewart",
      "character": null
    },
    {
      "personID": "0873158",
      "name": "Mike Tristano",
      "character": null
    },
    {
      "personID": "0933822",
      "name": "Mark Bryan Wilson",
      "character": null
    },
    {
      "personID": "0047355",
      "name": "Kim Bailey",
      "character": null
    }
  ],
  "visual effects": [
    {
      "personID": "0042138",
      "name": "Jim Aupperle",
      "character": null
    },
    {
      "personID": "0051101",
      "name": "James Balsam",
      "character": null
    },
    {
      "personID": "0131011",
      "name": "Yancy Calzada",
      "character": null
    },
    {
      "personID": "0163794",
      "name": "Craig Clark",
      "character": null
    },
    {
      "personID": "0404438",
      "name": "Clint Hutchison",
      "character": null
    },
    {
      "personID": "0453139",
      "name": "Crit Killen",
      "character": null
    },
    {
      "personID": "0558047",
      "name": "Jeff Matakovich",
      "character": null
    },
    {
      "personID": "0601088",
      "name": "Dan Moore",
      "character": null
    },
    {
      "personID": "0611309",
      "name": "George Muhs",
      "character": null
    },
    {
      "personID": "0717769",
      "name": "William Reilly",
      "character": null
    },
    {
      "personID": "0847821",
      "name": "Michael Talarico",
      "character": null
    },
    {
      "personID": "0884239",
      "name": "James Valentine",
      "character": null
    },
    {
      "personID": "0947087",
      "name": "Hoyt Yeatman",
      "character": null
    }
  ],
  "stunt performer": [
    {
      "personID": "0054979",
      "name": "Rick Barker",
      "character": null
    },
    {
      "personID": "0112991",
      "name": "Alison Brown",
      "character": null
    },
    {
      "personID": "0191857",
      "name": "Bob K. Cummings",
      "character": null
    },
    {
      "personID": "0199272",
      "name": "Gregg Dandridge",
      "character": null
    },
    {
      "personID": "0318331",
      "name": "Joe Gilbride",
      "character": null
    },
    {
      "personID": "0514724",
      "name": "Gary Littlejohn",
      "character": null
    },
    {
      "personID": "0604551",
      "name": "Charly Morgan",
      "character": null
    },
    {
      "personID": "0675360",
      "name": "William R. Perry",
      "character": null
    },
    {
      "personID": "0692086",
      "name": "Debby Porter",
      "character": null
    },
    {
      "personID": "0799099",
      "name": "J.D. Silvester",
      "character": null
    },
    {
      "personID": "0793372",
      "name": "Tony Snegoff",
      "character": null
    }
  ],
  "camera and electrical department": [
    {
      "personID": "0008200",
      "name": "Antar Abderrahman Jr.",
      "character": null
    },
    {
      "personID": "0077010",
      "name": "Brian Bernstein",
      "character": null
    },
    {
      "personID": "0136596",
      "name": "Michael Cardone",
      "character": null
    },
    {
      "personID": "0230581",
      "name": "John Doherty",
      "character": null
    },
    {
      "personID": "0242946",
      "name": "Giles Dunning",
      "character": null
    },
    {
      "personID": "0446866",
      "name": "Shane D. Kelly",
      "character": null
    },
    {
      "personID": "0616652",
      "name": "Bob Myers",
      "character": null
    },
    {
      "personID": "0006701",
      "name": "John Schwartzman",
      "character": null
    },
    {
      "personID": "0800274",
      "name": "Mark Simon",
      "character": null
    },
    {
      "personID": "0004604",
      "name": "Bruce Swift",
      "character": null
    },
    {
      "personID": "0925683",
      "name": "Eric Whitehead",
      "character": null
    }
  ],
  "animation department": [
    {
      "personID": "0079068",
      "name": "Doug Beswick",
      "character": null
    }
  ],
  "casting department": [
    {
      "personID": "3162452",
      "name": "Andrea Curtis",
      "character": null
    }
  ],
  "costume department": [
    {
      "personID": "0758764",
      "name": "Donna R. Schultz",
      "character": null
    }
  ],
  "location management": [
    {
      "personID": "0134177",
      "name": "David T. Cannon",
      "character": null
    }
  ],
  "music department": [
    {
      "personID": "0057059",
      "name": "Andrew Barrett",
      "character": null
    },
    {
      "personID": "0017450",
      "name": "Charles Bernstein",
      "character": null
    },
    {
      "personID": "0149384",
      "name": "David Chackler",
      "character": null
    },
    {
      "personID": "0230711",
      "name": "Don Dokken",
      "character": null
    },
    {
      "personID": "0149536",
      "name": "Earl Ghaffari",
      "character": null
    },
    {
      "personID": "0365697",
      "name": "Ken Harrison",
      "character": null
    },
    {
      "personID": "0633317",
      "name": "Ray Niznik",
      "character": null
    },
    {
      "personID": "0878092",
      "name": "Joseph Turrin",
      "character": null
    },
    {
      "personID": "0000823",
      "name": "Angelo Badalamenti",
      "character": null
    },
    {
      "personID": "1178264",
      "name": "Mick Brown",
      "character": null
    },
    {
      "personID": "0528304",
      "name": "George Lynch",
      "character": null
    },
    {
      "personID": "0683662",
      "name": "Jeff Pilson",
      "character": null
    },
    {
      "personID": "4012803",
      "name": "John Andrew Schreiner",
      "character": null
    },
    {
      "personID": "5015850",
      "name": "Tony Selvage",
      "character": null
    }
  ],
  "script department": [
    {
      "personID": "0262842",
      "name": "J. Ellen Evans",
      "character": null
    }
  ],
  "transportation department": [
    {
      "personID": "1740655",
      "name": "David Walden Sr.",
      "character": null
    }
  ],
  "miscellaneous crew": [
    {
      "personID": "0048289",
      "name": "Brent Baker",
      "character": null
    },
    {
      "personID": "0086601",
      "name": "John Blake",
      "character": null
    },
    {
      "personID": "0086849",
      "name": "Ella St. John Blakey",
      "character": null
    },
    {
      "personID": "0123060",
      "name": "Everett Burrell",
      "character": null
    },
    {
      "personID": "0139293",
      "name": "Cathy Carpenter",
      "character": null
    },
    {
      "personID": "0176583",
      "name": "Blaine Converse",
      "character": null
    },
    {
      "personID": "0188526",
      "name": "Gino Crognale",
      "character": null
    },
    {
      "personID": "0222191",
      "name": "Mitch Devane",
      "character": null
    },
    {
      "personID": "3559776",
      "name": "Steven E Dunn",
      "character": null
    },
    {
      "personID": "0249446",
      "name": "Keith Edmier",
      "character": null
    },
    {
      "personID": "0254814",
      "name": "Earl Ellis",
      "character": null
    },
    {
      "personID": "0416946",
      "name": "Steven James",
      "character": null
    },
    {
      "personID": "0434610",
      "name": "James Kagel",
      "character": null
    },
    {
      "personID": "0440343",
      "name": "June Kim",
      "character": null
    },
    {
      "personID": "0454316",
      "name": "David Kindlon",
      "character": null
    },
    {
      "personID": "0476071",
      "name": "Robert Kurtzman",
      "character": null
    },
    {
      "personID": "0523068",
      "name": "Tom Lowe",
      "character": null
    },
    {
      "personID": "0572935",
      "name": "James McLoughlin",
      "character": null
    },
    {
      "personID": "0601104",
      "name": "Deborah Moore",
      "character": null
    },
    {
      "personID": "0644072",
      "name": "Larry Odien",
      "character": null
    },
    {
      "personID": "0671883",
      "name": "Brian Penikas",
      "character": null
    },
    {
      "personID": "0674635",
      "name": "Dan Perri",
      "character": null
    },
    {
      "personID": "0782516",
      "name": "Russell Seifert",
      "character": null
    },
    {
      "personID": "0851552",
      "name": "Bryant Tausek",
      "character": null
    },
    {
      "personID": "0878135",
      "name": "Jon Turtle",
      "character": null
    },
    {
      "personID": "0904418",
      "name": "John Vulich",
      "character": null
    },
    {
      "personID": "1271034",
      "name": "Don Wyse",
      "character": null
    }
  ],
  "thanks": [
    {
      "personID": "0009275",
      "name": "Stephen Abramson",
      "character": null
    },
    {
      "personID": "11644683",
      "name": "Chris Barden",
      "character": null
    },
    {
      "personID": "6489692",
      "name": "Mike Bone",
      "character": null
    },
    {
      "personID": "11644677",
      "name": "Lisa Brown",
      "character": null
    },
    {
      "personID": "1452753",
      "name": "Gary Casson",
      "character": null
    },
    {
      "personID": "11644676",
      "name": "Doris Cutler",
      "character": null
    },
    {
      "personID": "5387339",
      "name": "George Dassinger",
      "character": null
    },
    {
      "personID": "11644678",
      "name": "Frank Gruber",
      "character": null
    },
    {
      "personID": "0364021",
      "name": "Michael Harpster",
      "character": null
    },
    {
      "personID": "11644681",
      "name": "Byron Hontaf",
      "character": null
    },
    {
      "personID": "11644682",
      "name": "Brad Hunt",
      "character": null
    },
    {
      "personID": "1450387",
      "name": "Bob Krasnow",
      "character": null
    },
    {
      "personID": "1604298",
      "name": "Ken Manson Jr.",
      "character": null
    },
    {
      "personID": "11644684",
      "name": "Charles Ryan",
      "character": null
    },
    {
      "personID": "1205860",
      "name": "Robin Sloane",
      "character": null
    },
    {
      "personID": "11644680",
      "name": "Barbara Theard",
      "character": null
    },
    {
      "personID": "11644679",
      "name": "Ben Zinken",
      "character": null
    }
  ],
  "akas": [
    "A Nightmare on Elm Street 3 (World-wide, English title)",
    "Les Griffes du cauchemar (France)",
    "Freddy 3: Les Griffes du cauchemar (France)",
    "Nightmare 3 - Freddy lebt (Germany)",
    "Pesadilla en Elm Street 3 (Spain)"
  ],
  "production companies": [
    {
      "companyID": "0046718",
      "name": "New Line Cinema"
    },
    {
      "companyID": "0052823",
      "name": "Heron Communications"
    },
    {
      "companyID": "0039541",
      "name": "Smart Egg Pictures"
    },
    {
      "companyID": "0056510",
      "name": "The New Line-Heron Joint Venture"
    }
  ],
  "distributors": [
    {
      "companyID": "0046718",
      "name": "New Line Cinema"
    },
    {
      "companyID": "0149423",
      "name": "VideoVisa"
    },
    {
      "companyID": "0010132",
      "name": "Astral Films"
    },
    {
      "companyID": "0110680",
      "name": "Eurogroup"
    },
    {
      "companyID": "0034882",
      "name": "Heraldo Films S.A."
    },
    {
      "companyID": "0103598",
      "name": "Palace Pictures"
    },
    {
      "companyID": "0037510",
      "name": "Seven Keys"
    },
    {
      "companyID": "0504146",
      "name": "Warner Home Video"
    },
    {
      "companyID": "0025931",
      "name": "Astral Video"
    },
    {
      "companyID": "0057219",
      "name": "Media Home Entertainment"
    },
    {
      "companyID": "0229488",
      "name": "Delta Filmverleih"
    },
    {
      "companyID": "0112570",
      "name": "Succ\u00e9film AB"
    },
    {
      "companyID": "0002663",
      "name": "Warner Bros."
    },
    {
      "companyID": "0059995",
      "name": "Warner Home Video"
    },
    {
      "companyID": "0013585",
      "name": "Image Entertainment"
    },
    {
      "companyID": "0006383",
      "name": "Warner Home Video"
    },
    {
      "companyID": "0094757",
      "name": "Warner Home Video"
    },
    {
      "companyID": "0087314",
      "name": "Warner Home Video"
    },
    {
      "companyID": "0189793",
      "name": "Warner Home Video"
    },
    {
      "companyID": "0014957",
      "name": "USA Network"
    },
    {
      "companyID": "0050978",
      "name": "HGV Video Productions"
    },
    {
      "companyID": "0019190",
      "name": "Elite Entertainment"
    },
    {
      "companyID": "0090512",
      "name": "Alliance Atlantis Home Video"
    },
    {
      "companyID": "0079450",
      "name": "New Line Home Video"
    },
    {
      "companyID": "0190332",
      "name": "RCV Home Entertainment"
    },
    {
      "companyID": "0090512",
      "name": "Alliance Atlantis Home Video"
    },
    {
      "companyID": "0059732",
      "name": "TriPictures"
    },
    {
      "companyID": "0059995",
      "name": "Warner Home Video"
    },
    {
      "companyID": "0238173",
      "name": "Front Row Filmed Entertainment"
    },
    {
      "companyID": "0363588",
      "name": "Europa Vision"
    },
    {
      "companyID": "0021161",
      "name": "Paris Filmes"
    },
    {
      "companyID": "0028557",
      "name": "Canal+"
    },
    {
      "companyID": "0523825",
      "name": "Elea Media"
    },
    {
      "companyID": "0046830",
      "name": "Embassy Communications"
    },
    {
      "companyID": "0363592",
      "name": "FS Film"
    },
    {
      "companyID": "0127113",
      "name": "Fazer Musiikki Oy/Fazer Video"
    },
    {
      "companyID": "0754095",
      "name": "HBO Max"
    },
    {
      "companyID": "0079450",
      "name": "New Line Home Video"
    },
    {
      "companyID": "0239044",
      "name": "Playarte Pictures"
    },
    {
      "companyID": "0112383",
      "name": "RTL Entertainment"
    },
    {
      "companyID": "0050310",
      "name": "Sandrew Metronome Distribution"
    },
    {
      "companyID": "0053518",
      "name": "Video Treasures"
    }
  ],
  "special effects companies": [
    {
      "companyID": "0058110",
      "name": "Cinema Research"
    },
    {
      "companyID": "0042356",
      "name": "Dream Quest Images"
    }
  ],
  "other companies": [
    {
      "companyID": "0012439",
      "name": "Clairmont Camera Film & Digital"
    },
    {
      "companyID": "0032603",
      "name": "Creative Casting"
    }
  ]
}